README.md
setup.py
pulumi_yandex_unofficial/__init__.py
pulumi_yandex_unofficial/_inputs.py
pulumi_yandex_unofficial/_utilities.py
pulumi_yandex_unofficial/alb_backend_group.py
pulumi_yandex_unofficial/alb_http_router.py
pulumi_yandex_unofficial/alb_load_balancer.py
pulumi_yandex_unofficial/alb_target_group.py
pulumi_yandex_unofficial/alb_virtual_host.py
pulumi_yandex_unofficial/api_gateway.py
pulumi_yandex_unofficial/backup_policy.py
pulumi_yandex_unofficial/cdn_origin_group.py
pulumi_yandex_unofficial/cdn_resource.py
pulumi_yandex_unofficial/cm_certificate.py
pulumi_yandex_unofficial/compute_disk.py
pulumi_yandex_unofficial/compute_disk_placement_group.py
pulumi_yandex_unofficial/compute_gpu_cluster.py
pulumi_yandex_unofficial/compute_image.py
pulumi_yandex_unofficial/compute_instance.py
pulumi_yandex_unofficial/compute_instance_group.py
pulumi_yandex_unofficial/compute_placement_group.py
pulumi_yandex_unofficial/compute_snapshot.py
pulumi_yandex_unofficial/compute_snapshot_schedule.py
pulumi_yandex_unofficial/container_registry.py
pulumi_yandex_unofficial/container_registry_iam_binding.py
pulumi_yandex_unofficial/container_registry_ip_permission.py
pulumi_yandex_unofficial/container_repository.py
pulumi_yandex_unofficial/container_repository_iam_binding.py
pulumi_yandex_unofficial/container_repository_lifecycle_policy.py
pulumi_yandex_unofficial/dataproc_cluster.py
pulumi_yandex_unofficial/datatransfer_endpoint.py
pulumi_yandex_unofficial/datatransfer_transfer.py
pulumi_yandex_unofficial/dns_record_set.py
pulumi_yandex_unofficial/dns_zone.py
pulumi_yandex_unofficial/function.py
pulumi_yandex_unofficial/function_iam_binding.py
pulumi_yandex_unofficial/function_scaling_policy.py
pulumi_yandex_unofficial/function_trigger.py
pulumi_yandex_unofficial/get_alb_backend_group.py
pulumi_yandex_unofficial/get_alb_http_router.py
pulumi_yandex_unofficial/get_alb_load_balancer.py
pulumi_yandex_unofficial/get_alb_target_group.py
pulumi_yandex_unofficial/get_alb_virtual_host.py
pulumi_yandex_unofficial.egg-info/PKG-INFO
pulumi_yandex_unofficial.egg-info/SOURCES.txt
pulumi_yandex_unofficial.egg-info/dependency_links.txt
pulumi_yandex_unofficial.egg-info/not-zip-safe
pulumi_yandex_unofficial.egg-info/requires.txt
pulumi_yandex_unofficial.egg-info/top_level.txt
