Metadata-Version: 2.1
Name: pulumi-yandex-unofficial
Version: 0.99.1
Summary: A Pulumi package for creating and managing yandex cloud resources.
Home-page: https://www.pulumi.com
License: Apache-2.0
Project-URL: Repository, https://github.com/regrau/pulumi-yandex
Keywords: pulumi yandex category/cloud
Platform: UNKNOWN
